fforward/__init__.py
fforward/py.typed
fforward/src.py
fforward-0.1.2.dist-info/LICENSE
fforward-0.1.2.dist-info/WHEEL
fforward-0.1.2.dist-info/METADATA
fforward-0.1.2.dist-info/RECORD
