Metadata-Version: 2.1
Name: fforward
Version: 0.1.2
Summary: 
Author: TheGreen
Requires-Python: >=3.11,<4.0
Classifier: Programming Language :: Python :: 3
Classifier: Programming Language :: Python :: 3.11
Requires-Dist: fastapi (>=0.103.2,<0.104.0)
Requires-Dist: sqlalchemy (>=2.0.22,<3.0.0)
